gencodedoc/__init__.py
gencodedoc/__main__.py
gencodedoc/cli/__init__.py
gencodedoc/cli/config_cmd.py
gencodedoc/cli/doc_cmd.py
gencodedoc/cli/main.py
gencodedoc/cli/mcp_cmd.py
gencodedoc/cli/snapshot_cmd.py
gencodedoc/core/__init__.py
gencodedoc/core/autosave.py
gencodedoc/core/config.py
gencodedoc/core/differ.py
gencodedoc/core/documentation.py
gencodedoc/core/scanner.py
gencodedoc/core/versioning.py
gencodedoc/mcp/__init__.py
gencodedoc/mcp/server.py
gencodedoc/mcp/server_sse.py
gencodedoc/mcp/server_stdio.py
gencodedoc/mcp/tools.py
gencodedoc/models/__init__.py
gencodedoc/models/config.py
gencodedoc/models/snapshot.py
gencodedoc/storage/__init__.py
gencodedoc/storage/compression.py
gencodedoc/storage/database.py
gencodedoc/storage/snapshot_store.py
gencodedoc/utils/__init__.py
gencodedoc/utils/filters.py
gencodedoc/utils/formatters.py
gencodedoc/utils/tree.py
gencodedoc-2.0.1.dist-info/METADATA
gencodedoc-2.0.1.dist-info/WHEEL
gencodedoc-2.0.1.dist-info/entry_points.txt
gencodedoc-2.0.1.dist-info/licenses/LICENSE
gencodedoc-2.0.1.dist-info/RECORD
