Metadata-Version: 2.4
Name: gencodedoc
Version: 2.0.1
Summary: Smart documentation generator and intelligent versioning system with MCP support
License: MIT
License-File: LICENSE
Keywords: documentation,versioning,mcp,snapshot,diff,ai-tools
Author: fkom13
Author-email: geminiEA@mail.com
Requires-Python: >=3.10,<4.0
Classifier: Development Status :: 4 - Beta
Classifier: Intended Audience :: Developers
Classifier: License :: OSI Approved :: MIT License
Classifier: Programming Language :: Python :: 3
Classifier: Programming Language :: Python :: 3.10
Classifier: Programming Language :: Python :: 3.11
Classifier: Programming Language :: Python :: 3.12
Classifier: Programming Language :: Python :: 3.13
Classifier: Programming Language :: Python :: 3.14
Classifier: Topic :: Software Development :: Documentation
Classifier: Topic :: Software Development :: Version Control
Requires-Dist: aiofiles (>=23.2.1,<24.0.0)
Requires-Dist: fastapi (>=0.121.0,<0.122.0)
Requires-Dist: httpx (>=0.25.2,<0.26.0)
Requires-Dist: pathspec (>=0.11.2,<0.12.0)
Requires-Dist: pydantic (>=2.5.0,<3.0.0)
Requires-Dist: pydantic-settings (>=2.1.0,<3.0.0)
Requires-Dist: python-multipart (>=0.0.6,<0.0.7)
Requires-Dist: pyyaml (>=6.0.1,<7.0.0)
Requires-Dist: rich (>=13.7.0,<14.0.0)
Requires-Dist: typer[all] (>=0.20.0,<0.21.0)
Requires-Dist: uvicorn (>=0.38.0,<0.39.0)
Requires-Dist: watchdog (>=3.0.0,<4.0.0)
Requires-Dist: zstandard (>=0.22.0,<0.23.0)
Project-URL: Homepage, https://github.com/fkom13/gencodedoc
Project-URL: Repository, https://github.com/fkom13/gencodedoc
